{
    "training_time": 26.2565,
    "training_samples": 394,
    "data_info": {
        "commonsense_qa": {
            "train_indices": [
                906,
                9464,
                4713,
                2362,
                5173,
                2781,
                8402,
                400,
                1055,
                7472,
                500,
                7556,
                89,
                6022,
                7975,
                8753,
                9600,
                4838,
                3431,
                8446,
                3866,
                6269,
                199,
                7871,
                4184,
                5440,
                7589,
                3921,
                8844,
                6331,
                7084,
                7593,
                3416
            ],
            "val_indices": [
                113,
                1186,
                590,
                296,
                648,
                348,
                1053,
                50,
                132,
                936,
                62,
                947,
                11,
                754,
                999,
                1097,
                1203,
                606,
                430,
                1058,
                484,
                785,
                24,
                986,
                524,
                681,
                951,
                491,
                1108,
                793,
                887,
                951,
                428
            ],
            "train_size": 33,
            "val_size": 33
        },
        "gsm8k": {
            "train_indices": [
                695,
                7261,
                3615,
                1812,
                3969,
                2133,
                6446,
                307,
                809,
                5732,
                384,
                5796,
                68,
                4620,
                6118,
                6715,
                7365
            ],
            "val_indices": [
                122,
                1281,
                638,
                319,
                700,
                376,
                1137,
                54,
                142,
                1011,
                67,
                1023,
                12,
                815,
                1079,
                1185,
                1300
            ],
            "train_size": 17,
            "val_size": 17
        },
        "rowan_hellaswag": {
            "train_indices": [
                3715,
                38773,
                19308,
                9677,
                21194,
                11394,
                34423,
                1640,
                4323,
                30613,
                2052,
                30954,
                364,
                24673,
                32670,
                35858,
                39330,
                19822,
                14059,
                34601,
                15837,
                25685,
                816,
                32246,
                17143,
                22288,
                31090,
                16064,
                36233,
                25937,
                29021,
                31108,
                13995,
                784,
                14308,
                12100,
                36675
            ],
            "val_indices": [
                934,
                9757,
                4858,
                2435,
                5333,
                2867,
                8662,
                412,
                1088,
                7703,
                516,
                7789,
                91,
                6209,
                8221,
                9023,
                9897,
                4988,
                3537,
                8707,
                3985,
                6463,
                205,
                8114,
                4314,
                5608,
                7823,
                4042,
                9118,
                6526,
                7303,
                7828,
                3522,
                197,
                3600,
                3044,
                9229
            ],
            "train_size": 37,
            "val_size": 37
        },
        "pubmedqa": {
            "train_indices": [
                18621,
                194331,
                96771
            ],
            "val_indices": [
                1049,
                10949,
                5452
            ],
            "train_size": 3,
            "val_size": 3
        },
        "sciq": {
            "train_indices": [
                1087,
                11347,
                5651,
                2832,
                6202,
                3334,
                10074,
                480,
                1265,
                8959,
                600,
                9059,
                106,
                7221,
                9561,
                10494,
                11510,
                5801,
                4114,
                10126,
                4635,
                7517,
                238,
                9437,
                5017,
                6523,
                9099,
                4701,
                10604,
                7590,
                8493,
                9104,
                4096,
                229,
                4187,
                3541,
                10733,
                2959,
                2816,
                10626,
                9072,
                5019,
                10765,
                8265,
                838,
                3761,
                9870,
                7424,
                7187,
                9440,
                7432,
                3123,
                4502,
                4028,
                2339,
                3039,
                7856,
                9908,
                2368,
                9006,
                9706,
                6297,
                4349,
                2372,
                2194,
                3780,
                844,
                2256,
                10730,
                7166,
                435,
                3201,
                8447,
                10908,
                4650,
                8374,
                9523,
                355,
                9654
            ],
            "val_indices": [
                93,
                971,
                483,
                242,
                531,
                285,
                862,
                41,
                108,
                767,
                51,
                775,
                9,
                618,
                818,
                898,
                985,
                496,
                352,
                867,
                396,
                643,
                20,
                808,
                429,
                558,
                779,
                402,
                907,
                649,
                727,
                779,
                350,
                19,
                358,
                303,
                919,
                253,
                241,
                909,
                776,
                429,
                921,
                707,
                71,
                322,
                845,
                635,
                615,
                808,
                636,
                267,
                385,
                344,
                200,
                260,
                672,
                848,
                202,
                771,
                831,
                539,
                372,
                203,
                187,
                323,
                72,
                193,
                918,
                613,
                37,
                274,
                723,
                934,
                398,
                717,
                815,
                30,
                826
            ],
            "train_size": 79,
            "val_size": 79
        },
        "wikitext": {
            "train_indices": [
                3418,
                35677,
                17766,
                8904,
                19501,
                10484,
                31674,
                1509,
                3978,
                28168,
                1888,
                28482,
                335,
                22703,
                30061,
                32994,
                36189,
                18239,
                12936,
                31837,
                14572,
                23633,
                751,
                29671,
                15774,
                20508,
                28607,
                14781,
                33339,
                23865,
                26703,
                28623,
                12878,
                721,
                13165,
                11133,
                33746,
                9304,
                8854,
                33410,
                28523,
                15780,
                33846,
                25985,
                2635,
                11826,
                31031,
                23341,
                22595,
                29679,
                23368,
                9819,
                14156,
                12666,
                7355,
                9555,
                24700,
                31150,
                7445,
                28314,
                30516,
                19800,
                13676,
                7460,
                6900,
                11885,
                2655,
                7094,
                33735,
                22530,
                1368,
                10066,
                26558
            ],
            "val_indices": [
                350,
                3653,
                1819,
                911,
                1997,
                1073,
                3243,
                154,
                407,
                2884,
                193,
                2916,
                34,
                2324,
                3078,
                3378,
                3705,
                1867,
                1324,
                3260,
                1492,
                2420,
                76,
                3038,
                1615,
                2100,
                2929,
                1513,
                3414,
                2443,
                2734,
                2931,
                1318,
                73,
                1348,
                1140,
                3455,
                952,
                906,
                3421,
                2920,
                1615,
                3465,
                2660,
                269,
                1211,
                3177,
                2390,
                2313,
                3039,
                2393,
                1005,
                1449,
                1297,
                753,
                978,
                2529,
                3189,
                762,
                2899,
                3124,
                2027,
                1400,
                763,
                706,
                1217,
                271,
                726,
                3454,
                2307,
                140,
                1030,
                2719
            ],
            "train_size": 73,
            "val_size": 73
        },
        "mmlu": {
            "train_indices": [
                1307,
                13643,
                6794,
                3405,
                7458,
                4009,
                12113,
                577,
                1521,
                10772,
                722,
                10892,
                128,
                8682,
                11496,
                12617,
                13839,
                6975,
                4947,
                12175,
                5573,
                9038,
                287,
                11347,
                6032,
                7843,
                10940,
                5652,
                12750,
                9126,
                10212,
                10946,
                4924,
                276,
                5034,
                4257,
                12905,
                3558,
                3386,
                12777,
                10908,
                6034,
                12943,
                9937,
                1007,
                4522,
                11867,
                8926,
                8641,
                11350,
                8936,
                3755,
                5413,
                4843,
                2813,
                3654,
                9446,
                11912,
                2847,
                10828,
                11670,
                7572,
                5230,
                2853,
                2638,
                4545,
                1015,
                2713,
                12901,
                8616,
                523,
                3849,
                10156,
                13116,
                5591,
                10068,
                11450,
                427,
                11608,
                6712,
                3941,
                8342,
                887,
                2346
            ],
            "val_indices": [
                142,
                1487,
                740,
                371,
                813,
                437,
                1320,
                62,
                165,
                1174,
                78,
                1187,
                13,
                946,
                1253,
                1375,
                1508,
                760,
                539,
                1327,
                607,
                985,
                31,
                1237,
                657,
                855,
                1192,
                616,
                1390,
                995,
                1113,
                1193,
                536,
                30,
                548,
                464,
                1407,
                387,
                369,
                1393,
                1189,
                657,
                1411,
                1083,
                109,
                493,
                1293,
                973,
                942,
                1237,
                974,
                409,
                590,
                528,
                306,
                398,
                1029,
                1298,
                310,
                1180,
                1272,
                825,
                570,
                311,
                287,
                495,
                110,
                295,
                1406,
                939,
                57,
                419,
                1107,
                1430,
                609,
                1097,
                1248,
                46,
                1265,
                731,
                429,
                909,
                96,
                255
            ],
            "train_size": 84,
            "val_size": 84
        },
        "ai2_arc": {
            "train_indices": [
                104,
                1087,
                541,
                271,
                594,
                319,
                965,
                45,
                121,
                858,
                57,
                868,
                10,
                691,
                916,
                1005,
                1102,
                555,
                394,
                970,
                444,
                720,
                22,
                904,
                480,
                625,
                871,
                450,
                1016,
                727,
                813,
                872,
                392,
                21,
                401,
                339,
                1028,
                283,
                269,
                1018,
                869,
                480,
                1031,
                791,
                80,
                360,
                945,
                711,
                688,
                904,
                712,
                299,
                431,
                386,
                224,
                291,
                752,
                949,
                226,
                862,
                930,
                603,
                416,
                227,
                210,
                362,
                80,
                216
            ],
            "val_indices": [
                27,
                290,
                144,
                72,
                158,
                85,
                257,
                12,
                32,
                229,
                15,
                231,
                2,
                184,
                244,
                268,
                294,
                148,
                105,
                259,
                118,
                192,
                6,
                241,
                128,
                167,
                232,
                120,
                271,
                194,
                217,
                233,
                104,
                5,
                107,
                90,
                274,
                75,
                72,
                272,
                232,
                128,
                275,
                211,
                21,
                96,
                252,
                190,
                183,
                241,
                190,
                79,
                115,
                103,
                59,
                77,
                201,
                253,
                60,
                230,
                248,
                161,
                111,
                60,
                56,
                96,
                21,
                57
            ],
            "train_size": 68,
            "val_size": 68
        }
    }
}