{
    "training_time": 27.6138,
    "training_samples": 395,
    "data_info": {
        "gsm8k": {
            "train_indices": [
                3668,
                5628,
                6981,
                7166,
                1182,
                1240,
                2179,
                1870,
                1536,
                856,
                586,
                3072,
                4112,
                1360,
                16,
                1265,
                1097,
                7053,
                4359,
                3123,
                7260,
                2506,
                3811,
                3266,
                3898,
                6228,
                3150,
                667,
                4394,
                1179,
                2277,
                4242,
                5289,
                6506,
                6951,
                1425,
                7015,
                4267,
                7343,
                1893,
                3081,
                5238,
                5544
            ],
            "val_indices": [
                647,
                993,
                1232,
                1264,
                208,
                218,
                384,
                330,
                271,
                151,
                103,
                542,
                725,
                240,
                2,
                223,
                193,
                1244,
                769,
                551,
                1281,
                442,
                672,
                576,
                688,
                1099,
                556,
                117,
                775,
                208,
                401,
                748,
                933,
                1148,
                1226,
                251,
                1238,
                753,
                1296,
                334,
                543,
                924,
                978
            ],
            "train_size": 43,
            "val_size": 43
        },
        "headqa_en": {
            "train_indices": [
                1304,
                2001,
                2482,
                2547,
                420,
                441,
                774,
                664,
                546,
                304,
                208,
                1092,
                1462,
                483,
                5,
                449,
                390,
                2507,
                1550,
                1110,
                2581,
                891,
                1355,
                1161,
                1386,
                2214,
                1120,
                237,
                1562,
                419,
                809,
                1508,
                1880,
                2313,
                2471,
                506,
                2494,
                1517,
                2610,
                673,
                1095,
                1862,
                1971,
                466,
                1231,
                2263,
                171
            ],
            "val_indices": [
                670,
                1028,
                1276,
                1309,
                216,
                226,
                398,
                341,
                280,
                156,
                107,
                561,
                751,
                248,
                2,
                231,
                200,
                1289,
                796,
                570,
                1327,
                458,
                696,
                597,
                712,
                1138,
                575,
                122,
                803,
                215,
                416,
                775,
                966,
                1189,
                1270,
                260,
                1282,
                780,
                1342,
                346,
                563,
                957,
                1013,
                239,
                632,
                1163,
                88
            ],
            "train_size": 47,
            "val_size": 47
        },
        "rowan_hellaswag": {
            "train_indices": [
                19591,
                30058,
                37280,
                38267,
                6311,
                6623,
                11639,
                9986,
                8206,
                4573,
                3129,
                16408,
                21959,
                7265,
                87,
                6755,
                5860,
                37664,
                23281,
                16677,
                38769,
                13385,
                20352,
                17441,
                20819,
                33261,
                16823,
                3564,
                23463,
                6300,
                12160,
                22654,
                28243,
                34746,
                37119,
                7610,
                37462,
                22789,
                39210,
                10110,
                16455,
                27971,
                29609,
                7003,
                18490,
                34000,
                2574,
                13698,
                39575,
                35630
            ],
            "val_indices": [
                4930,
                7564,
                9381,
                9629,
                1588,
                1666,
                2929,
                2513,
                2065,
                1150,
                787,
                4129,
                5525,
                1828,
                22,
                1700,
                1474,
                9478,
                5858,
                4196,
                9756,
                3368,
                5121,
                4389,
                5239,
                8370,
                4233,
                896,
                5904,
                1585,
                3060,
                5700,
                7107,
                8743,
                9340,
                1915,
                9427,
                5735,
                9867,
                2544,
                4141,
                7039,
                7451,
                1762,
                4653,
                8556,
                647,
                3447,
                9959,
                8966
            ],
            "train_size": 50,
            "val_size": 50
        },
        "pubmedqa": {
            "train_indices": [
                98192,
                150648,
                186844,
                191792,
                31634,
                33196,
                58336,
                50052,
                41132,
                22921,
                15685,
                82236,
                110056,
                36412,
                438,
                33858,
                29371,
                188770,
                116684,
                83586,
                194309,
                67085,
                102006,
                87414,
                104344,
                166705,
                84316,
                17863,
                117598,
                31575,
                60949,
                113542,
                141552,
                174145,
                186038,
                38141,
                187758,
                114220,
                196521,
                50674,
                82474,
                140191,
                148399,
                35099,
                92674,
                170409,
                12902,
                68656,
                198351,
                178577,
                112952,
                92954,
                83983,
                171421,
                194458,
                81308,
                20631
            ],
            "val_indices": [
                5532,
                8488,
                10527,
                10806,
                1782,
                1870,
                3286,
                2820,
                2317,
                1291,
                883,
                4633,
                6201,
                2051,
                24,
                1907,
                1654,
                10636,
                6574,
                4709,
                10948,
                3779,
                5747,
                4925,
                5879,
                9393,
                4750,
                1006,
                6626,
                1779,
                3434,
                6397,
                7975,
                9812,
                10482,
                2149,
                10579,
                6435,
                11072,
                2855,
                4647,
                7899,
                8361,
                1977,
                5221,
                9601,
                727,
                3868,
                11176,
                10061,
                6364,
                5237,
                4732,
                9658,
                10956,
                4581,
                1162
            ],
            "train_size": 57,
            "val_size": 57
        },
        "sciq": {
            "train_indices": [
                5733,
                8797,
                10910,
                11199,
                1847,
                1938,
                3406,
                2922,
                2401,
                1338,
                915,
                4802,
                6426,
                2126,
                25,
                1977,
                1715,
                11023,
                6813,
                4881,
                11346,
                3917,
                5956,
                5104,
                6093,
                9734,
                4923,
                1043,
                6867,
                1843,
                3559,
                6630,
                8265,
                10169,
                10863,
                2227,
                10964,
                6669,
                11475,
                2959,
                4816,
                8186,
                8665,
                2049
            ],
            "val_indices": [
                490,
                753,
                934,
                958,
                158,
                165,
                291,
                250,
                205,
                114,
                78,
                411,
                550,
                182,
                2,
                169,
                146,
                943,
                583,
                417,
                971,
                335,
                510,
                437,
                521,
                833,
                421,
                89,
                587,
                157,
                304,
                567,
                707,
                870,
                930,
                190,
                938,
                571,
                982,
                253,
                412,
                700,
                741,
                175
            ],
            "train_size": 44,
            "val_size": 44
        },
        "triviaqa": {
            "train_indices": [
                67941,
                104237,
                129281,
                132704,
                21888,
                22969,
                40363,
                34632,
                28460,
                15859,
                10853,
                56901,
                76150,
                25194,
                303,
                23427,
                20322,
                130613,
                80736,
                57835,
                134446,
                46418,
                70580,
                60484,
                72197,
                115346,
                58340,
                12359,
                81368,
                21847,
                42171,
                78562,
                97942,
                120494,
                128723,
                26390,
                129913,
                79031,
                135976,
                35062,
                57065,
                97001,
                102680,
                24286,
                64123,
                117909,
                8927,
                47504,
                137243,
                123561,
                78153,
                64316,
                58109
            ],
            "val_indices": [
                8809,
                13516,
                16763,
                17207,
                2838,
                2978,
                5233,
                4490,
                3690,
                2056,
                1407,
                7378,
                9874,
                3266,
                39,
                3037,
                2635,
                16936,
                10468,
                7499,
                17433,
                6018,
                9152,
                7842,
                9361,
                14956,
                7564,
                1602,
                10550,
                2832,
                5468,
                10187,
                12700,
                15624,
                16691,
                3422,
                16845,
                10247,
                17631,
                4546,
                7399,
                12577,
                13314,
                3149,
                8314,
                15289,
                1157,
                6159,
                17796,
                16021,
                10134,
                8339,
                7535
            ],
            "train_size": 53,
            "val_size": 53
        },
        "truthfulqa_gen": {
            "train_indices": [
                401,
                615,
                763,
                783,
                129,
                135,
                238,
                204,
                168,
                93,
                64,
                335,
                449,
                148,
                1,
                138,
                119,
                771,
                476,
                341,
                793,
                274,
                416,
                357,
                426,
                680,
                344,
                72,
                480,
                128,
                248,
                463,
                578,
                711,
                759,
                155
            ],
            "val_indices": [
                401,
                615,
                763,
                783,
                129,
                135,
                238,
                204,
                168,
                93,
                64,
                335,
                449,
                148,
                1,
                138,
                119,
                771,
                476,
                341,
                793,
                274,
                416,
                357,
                426,
                680,
                344,
                72,
                480,
                128,
                248,
                463,
                578,
                711,
                759,
                155
            ],
            "train_size": 36,
            "val_size": 36
        },
        "wikitext": {
            "train_indices": [
                18027,
                27657,
                34302,
                35211,
                5807,
                6094,
                10709,
                9189,
                7551,
                4208,
                2879,
                15097,
                20205,
                6685,
                80,
                6216,
                5392,
                34656,
                21422,
                15345,
                35673,
                12316,
                18727,
                16048,
                19156,
                30605,
                15479,
                3279,
                21589,
                5796,
                11189,
                20845,
                25987,
                31971,
                34154,
                7002,
                34470,
                20969,
                36079,
                9303,
                15141,
                25737,
                27244,
                6443,
                17014,
                31285,
                2368,
                12604,
                36415,
                32785,
                20736,
                17065,
                15418,
                31471,
                35700,
                14927,
                3787,
                26898,
                6689
            ],
            "val_indices": [
                1846,
                2832,
                3512,
                3605,
                594,
                624,
                1096,
                940,
                773,
                430,
                294,
                1546,
                2069,
                684,
                8,
                636,
                552,
                3548,
                2193,
                1571,
                3653,
                1261,
                1917,
                1643,
                1961,
                3134,
                1585,
                335,
                2210,
                593,
                1145,
                2134,
                2661,
                3273,
                3497,
                717,
                3529,
                2147,
                3694,
                952,
                1550,
                2635,
                2789,
                659,
                1742,
                3203,
                242,
                1290,
                3729,
                3357,
                2123,
                1747,
                1578,
                3222,
                3655,
                1528,
                387,
                2754,
                685
            ],
            "train_size": 59,
            "val_size": 59
        },
        "mmlu": {
            "train_indices": [
                6894,
                10577,
                13118
            ],
            "val_indices": [
                751,
                1153,
                1430
            ],
            "train_size": 3,
            "val_size": 3
        },
        "ai2_arc": {
            "train_indices": [
                549,
                842,
                1045
            ],
            "val_indices": [
                146,
                225,
                279
            ],
            "train_size": 3,
            "val_size": 3
        }
    }
}