{
    "training_time": 43.9585,
    "training_samples": 994,
    "data_info": {
        "commonsense_qa": {
            "train_indices": [
                818,
                3810,
                6283,
                1390,
                6952,
                7867,
                5975,
                6363,
                5588,
                2101,
                8123,
                9107,
                4386,
                5332,
                4308,
                2208,
                9273,
                969,
                5806,
                2503,
                1165,
                3624,
                8589,
                257,
                4363,
                5534,
                1200,
                9392,
                4370,
                593,
                2797,
                3898,
                7542,
                9329,
                7763,
                9357,
                9003,
                9244,
                7034,
                7549,
                962,
                7422,
                5995,
                736,
                9280,
                5888,
                6884,
                110,
                1378,
                6832,
                5044,
                2874,
                9673,
                2227,
                8621,
                1709,
                8474,
                2122,
                5479,
                7688,
                7390,
                5008,
                2018,
                4418,
                7464,
                3601,
                7949,
                5556,
                7726,
                9217,
                2168,
                8154,
                7842,
                8605,
                8175,
                4475,
                1555,
                9380,
                9064,
                2745,
                8724,
                2661,
                5737,
                6624,
                840,
                9621,
                2958,
                9388,
                1170,
                6290,
                2057,
                5824,
                9365,
                1757,
                3259,
                7854,
                3138,
                6750,
                2685,
                1678,
                7505,
                4488,
                4883,
                3726,
                803,
                8943,
                6817,
                8341,
                3319,
                8002,
                7432,
                9289,
                8420,
                6929,
                5141,
                3393,
                102,
                8402,
                4424,
                5625,
                3195,
                4188,
                5467,
                8669,
                4157,
                2064,
                1038,
                8453,
                507,
                8108,
                4839,
                9357,
                7812,
                6603,
                514,
                8070,
                5680,
                2770,
                8679,
                9689,
                7905,
                5654,
                3390,
                4189,
                3767,
                9194,
                3238,
                3927,
                3189,
                3868,
                1091,
                355,
                3569,
                925,
                4949,
                925,
                5622,
                357,
                3554,
                5574,
                9564,
                2023,
                5002,
                4277,
                9349,
                997,
                8224,
                9187,
                8039,
                9046,
                3909,
                1005,
                1354,
                5143,
                5664,
                1799,
                5249,
                8753,
                1362,
                7390,
                5382,
                6527,
                4783,
                9564,
                6773,
                4193,
                3320,
                8177,
                5568,
                2401,
                5754,
                7534,
                2281,
                5992,
                7095,
                78
            ],
            "val_indices": [
                102,
                477,
                787,
                174,
                871,
                986,
                748,
                797,
                700,
                263,
                1018,
                1141,
                549,
                668,
                540,
                276,
                1162,
                121,
                727,
                313,
                146,
                454,
                1076,
                32,
                546,
                693,
                150,
                1177,
                547,
                74,
                350,
                488,
                945,
                1169,
                973,
                1172,
                1128,
                1158,
                881,
                946,
                120,
                930,
                751,
                92,
                1163,
                738,
                862,
                13,
                172,
                856,
                632,
                360,
                1212,
                279,
                1080,
                214,
                1062,
                265,
                686,
                963,
                926,
                627,
                252,
                553,
                935,
                451,
                996,
                696,
                968,
                1155,
                271,
                1022,
                982,
                1078,
                1024,
                561,
                195,
                1175,
                1136,
                344,
                1093,
                333,
                719,
                830,
                105,
                1206,
                370,
                1176,
                146,
                788,
                257,
                730,
                1173,
                220,
                408,
                984,
                393,
                846,
                336,
                210,
                940,
                562,
                612,
                467,
                100,
                1120,
                854,
                1045,
                416,
                1003,
                931,
                1164,
                1055,
                868,
                644,
                425,
                12,
                1053,
                554,
                705,
                400,
                524,
                685,
                1086,
                521,
                258,
                130,
                1059,
                63,
                1016,
                606,
                1172,
                979,
                827,
                64,
                1011,
                712,
                347,
                1088,
                1214,
                990,
                708,
                425,
                525,
                472,
                1152,
                405,
                492,
                399,
                484,
                136,
                44,
                447,
                115,
                620,
                116,
                704,
                44,
                445,
                698,
                1198,
                253,
                627,
                536,
                1171,
                125,
                1030,
                1151,
                1007,
                1133,
                490,
                126,
                169,
                644,
                710,
                225,
                657,
                1097,
                170,
                926,
                674,
                818,
                599,
                1198,
                849,
                525,
                416,
                1025,
                698,
                300,
                721,
                944,
                285,
                751,
                889,
                9
            ],
            "train_size": 196,
            "val_size": 196
        },
        "gsm8k": {
            "train_indices": [
                627,
                2923,
                4820,
                1067,
                5333,
                6035,
                4583,
                4881,
                4287,
                1612,
                6231,
                6986,
                3365,
                4091,
                3305,
                1694,
                7114,
                743,
                4454,
                1920,
                894,
                2780,
                6589,
                197,
                3347,
                4245,
                920,
                7205,
                3352,
                455,
                2146,
                2990,
                5786,
                7157,
                5956,
                7178,
                6907,
                7091,
                5396,
                5791,
                738,
                5694,
                4599,
                565,
                7119,
                4517,
                5281,
                84,
                1057,
                5241,
                3869,
                2204,
                7421,
                1708,
                6613,
                1311,
                6501,
                1628,
                4203,
                5898,
                5669,
                3842,
                1548,
                3389,
                5726,
                2763,
                6098,
                4262,
                5927,
                7071,
                1663,
                6256,
                6016,
                6601,
                6272,
                3433
            ],
            "val_indices": [
                110,
                516,
                850,
                188,
                941,
                1065,
                809,
                861,
                756,
                284,
                1099,
                1233,
                594,
                722,
                583,
                299,
                1255,
                131,
                786,
                339,
                157,
                490,
                1163,
                34,
                590,
                749,
                162,
                1271,
                591,
                80,
                378,
                527,
                1021,
                1263,
                1051,
                1267,
                1219,
                1251,
                952,
                1022,
                130,
                1005,
                811,
                99,
                1256,
                797,
                932,
                14,
                186,
                925,
                683,
                389,
                1309,
                301,
                1167,
                231,
                1147,
                287,
                741,
                1041,
                1000,
                678,
                273,
                598,
                1010,
                487,
                1076,
                752,
                1046,
                1248,
                293,
                1104,
                1061,
                1165,
                1107,
                606
            ],
            "train_size": 76,
            "val_size": 76
        },
        "rowan_hellaswag": {
            "train_indices": [
                3352,
                15611,
                25739,
                5698,
                28482,
                32228,
                24477,
                26066,
                22893,
                8609,
                33278,
                37307,
                17971,
                21846,
                17649,
                9046,
                37989,
                3970,
                23786,
                10257,
                4774,
                14849,
                35188,
                1055,
                17873,
                22670,
                4916,
                38476,
                17904,
                2430,
                11460,
                15971,
                30897,
                38220,
                31805,
                38333,
                36884,
                37869,
                28817,
                30926,
                3941,
                30407,
                24559,
                3018,
                38017,
                24124,
                28202,
                452,
                5647,
                27988,
                20663,
                11774,
                39628,
                9125,
                35317,
                7001,
                34718,
                8693,
                22446,
                31497,
                30274,
                20516,
                8268,
                18101,
                30580,
                14755,
                32565,
                22761,
                31653,
                37759,
                8885,
                33406,
                32125,
                35252,
                33492,
                18334,
                6374,
                38428,
                37135,
                11248,
                35740,
                10903,
                23502,
                27139,
                3441,
                39417,
                12118,
                38461,
                4794,
                25770,
                8427,
                23858,
                38365,
                7198,
                13353,
                32175,
                12855,
                27652,
                11001,
                6876,
                30747,
                18388,
                20007,
                15266,
                3290,
                36636,
                27928,
                34170,
                13596,
                32782,
                30446,
                38053,
                34493,
                28387,
                21062,
                13899,
                421,
                34422,
                18125,
                23045,
                13090,
                17158,
                22399,
                35514,
                17031,
                8456,
                4254,
                34631,
                2080,
                33215,
                19826,
                38332,
                32005,
                27050,
                2108,
                33061,
                23270,
                11347,
                35558
            ],
            "val_indices": [
                843,
                3928,
                6477,
                1433,
                7167,
                8110,
                6159,
                6559,
                5760,
                2166,
                8374,
                9388,
                4522,
                5497,
                4441,
                2276,
                9560,
                999,
                5985,
                2581,
                1201,
                3736,
                8855,
                265,
                4497,
                5705,
                1237,
                9682,
                4505,
                611,
                2883,
                4019,
                7775,
                9618,
                8003,
                9646,
                9281,
                9529,
                7251,
                7782,
                991,
                7651,
                6180,
                759,
                9567,
                6070,
                7096,
                113,
                1421,
                7043,
                5200,
                2962,
                9972,
                2296,
                8887,
                1761,
                8736,
                2187,
                5648,
                7926,
                7618,
                5163,
                2080,
                4555,
                7695,
                3713,
                8195,
                5727,
                7965,
                9502,
                2235,
                8406,
                8084,
                8871,
                8428,
                4613,
                1604,
                9670,
                9345,
                2830,
                8994,
                2743,
                5914,
                6829,
                865,
                9919,
                3049,
                9678,
                1206,
                6485,
                2120,
                6004,
                9654,
                1811,
                3360,
                8096,
                3235,
                6958,
                2768,
                1730,
                7737,
                4627,
                5034,
                3841,
                828,
                9219,
                7028,
                8598,
                3421,
                8249,
                7661,
                9576,
                8680,
                7143,
                5300,
                3497,
                106,
                8662,
                4561,
                5799,
                3294,
                4317,
                5636,
                8937,
                4286,
                2128,
                1070,
                8714,
                523,
                8358,
                4989,
                9646,
                8054,
                6807,
                530,
                8319,
                5855,
                2855,
                8948
            ],
            "train_size": 139,
            "val_size": 139
        },
        "pubmedqa": {
            "train_indices": [
                16802,
                78242,
                129004,
                28558,
                142750,
                161525,
                122679,
                130644,
                114737,
                43148,
                166786,
                186983,
                90069,
                109492,
                88459,
                45342,
                190401,
                19901,
                119215,
                51409,
                23929,
                74422,
                176359,
                5291,
                89580,
                113624,
                24640
            ],
            "val_indices": [
                946,
                4408,
                7268,
                1609,
                8043,
                9101,
                6912,
                7361,
                6464,
                2431,
                9397,
                10535,
                5074,
                6169,
                4984,
                2554,
                10728,
                1121,
                6717,
                2896,
                1348,
                4193,
                9936,
                298,
                5047,
                6402,
                1388
            ],
            "train_size": 27,
            "val_size": 27
        },
        "sciq": {
            "train_indices": [
                981,
                4568,
                7533,
                1667,
                8335,
                9432,
                7163,
                7628,
                6700,
                2519,
                9739,
                10918,
                5259,
                6393,
                5165,
                2647,
                11118,
                1162,
                6961,
                3002,
                1397,
                4345,
                10298,
                309,
                5231,
                6635
            ],
            "val_indices": [
                84,
                391,
                645,
                142,
                713,
                807,
                613,
                653,
                573,
                215,
                833,
                934,
                450,
                547,
                442,
                226,
                952,
                99,
                596,
                257,
                119,
                372,
                881,
                26,
                447,
                568
            ],
            "train_size": 26,
            "val_size": 26
        },
        "triviaqa": {
            "train_indices": [
                11625,
                54137,
                89260,
                19760,
                98772,
                111762,
                84884,
                90395,
                79389,
                29855,
                115402,
                129377,
                62321,
                75759,
                61206,
                31373,
                131742,
                13769,
                82487,
                35571,
                16557,
                51494,
                122026,
                3661,
                61982,
                78619,
                17049,
                133428,
                62089,
                8427,
                39741,
                55385,
                107146,
                132541,
                110295,
                132933,
                127909,
                131325,
                99933,
                107247,
                13667,
                105448,
                85168,
                10468,
                131839,
                83659,
                97800,
                1567,
                19586,
                97058,
                71659,
                40831,
                137426,
                31644,
                122475,
                24280,
                120397,
                30147,
                77842,
                109226,
                104986,
                71149,
                28672,
                62771,
                106047,
                51168,
                112932,
                78932,
                109770,
                130943,
                30813,
                115849,
                111407,
                122251,
                116147,
                63582,
                22104,
                133263,
                128779,
                39008,
                123943,
                37813,
                81502,
                94113,
                11933,
                136691,
                42023,
                133378,
                16627,
                89369,
                29226,
                82739,
                133045,
                24963,
                46309,
                111578,
                44582,
                95893,
                38151,
                23845,
                106627,
                63766,
                69382,
                52940,
                11412,
                127048,
                96850,
                118498,
                47151,
                113684,
                105581,
                131963,
                119617,
                98442,
                73040,
                48202,
                1463,
                119370,
                62856,
                79918,
                45393,
                59501,
                77679,
                123159,
                59063,
                29326,
                14753,
                120096,
                7213,
                115187,
                68755,
                132931,
                110990,
                93806,
                7311,
                114651,
                80697,
                39352,
                123310,
                137657,
                112313,
                80328,
                48171,
                59512,
                53521,
                130623
            ],
            "val_indices": [
                1507,
                7019,
                11574,
                2562,
                12807,
                14492,
                11006,
                11721,
                10294,
                3871,
                14964,
                16776,
                8081,
                9823,
                7936,
                4068,
                17082,
                1785,
                10696,
                4612,
                2146,
                6677,
                15822,
                474,
                8037,
                10194,
                2210,
                17301,
                8051,
                1092,
                5153,
                7181,
                13893,
                17186,
                14301,
                17237,
                16585,
                17028,
                12958,
                13906,
                1772,
                13673,
                11043,
                1357,
                17095,
                10847,
                12681,
                203,
                2539,
                12585,
                9291,
                5294,
                17819,
                4103,
                15881,
                3148,
                15611,
                3909,
                10093,
                14163,
                13613,
                9225,
                3717,
                8139,
                13751,
                6634,
                14643,
                10235,
                14233,
                16979,
                3995,
                15021,
                14445,
                15852,
                15060,
                8244,
                2866,
                17279,
                16698,
                5058,
                16071,
                4903,
                10568,
                12203,
                1547,
                17724,
                5449,
                17294,
                2156,
                11588,
                3789,
                10728,
                17251,
                3236,
                6004,
                14468,
                5780,
                12434,
                4947,
                3092,
                13826,
                8268,
                8996,
                6864,
                1479,
                16474,
                12558,
                15365,
                6114,
                14741,
                13690,
                17111,
                15510,
                12764,
                9470,
                6250,
                189,
                15478,
                8150,
                10362,
                5886,
                7715,
                10072,
                15969,
                7658,
                3802,
                1913,
                15572,
                935,
                14936,
                8915,
                17236,
                14391,
                12163,
                948,
                14866,
                10463,
                5102,
                15989,
                17849,
                14563,
                10416,
                6246,
                7716,
                6940,
                16937
            ],
            "train_size": 146,
            "val_size": 146
        },
        "truthfulqa_gen": {
            "train_indices": [
                68,
                319,
                526,
                116,
                583,
                659,
                501,
                533,
                468,
                176,
                681,
                763,
                367,
                447,
                361,
                185,
                777,
                81,
                486,
                210,
                97,
                304,
                720,
                21,
                365,
                464,
                100,
                787,
                366,
                49,
                234,
                326,
                632,
                782,
                651,
                784,
                755,
                775,
                589,
                633,
                80,
                622,
                502,
                61,
                778,
                493,
                577,
                9,
                115,
                573,
                423,
                241,
                811,
                186,
                723,
                143,
                710,
                177,
                459,
                644,
                619,
                420,
                169,
                370,
                626,
                302,
                666,
                466,
                648,
                773,
                181,
                683,
                657,
                721,
                685,
                375,
                130,
                786,
                760,
                230,
                731,
                223,
                481,
                555,
                70,
                807,
                248,
                787,
                98,
                527,
                172,
                488,
                785,
                147,
                273,
                658,
                263,
                566,
                225,
                140,
                629,
                376,
                409,
                312,
                67,
                750,
                571,
                699,
                278,
                671,
                623,
                779,
                706,
                581,
                431,
                284,
                8,
                704,
                371,
                471,
                267,
                351,
                458,
                727,
                348,
                173,
                87,
                709,
                42,
                680,
                405,
                784,
                655
            ],
            "val_indices": [
                68,
                319,
                526,
                116,
                583,
                659,
                501,
                533,
                468,
                176,
                681,
                763,
                367,
                447,
                361,
                185,
                777,
                81,
                486,
                210,
                97,
                304,
                720,
                21,
                365,
                464,
                100,
                787,
                366,
                49,
                234,
                326,
                632,
                782,
                651,
                784,
                755,
                775,
                589,
                633,
                80,
                622,
                502,
                61,
                778,
                493,
                577,
                9,
                115,
                573,
                423,
                241,
                811,
                186,
                723,
                143,
                710,
                177,
                459,
                644,
                619,
                420,
                169,
                370,
                626,
                302,
                666,
                466,
                648,
                773,
                181,
                683,
                657,
                721,
                685,
                375,
                130,
                786,
                760,
                230,
                731,
                223,
                481,
                555,
                70,
                807,
                248,
                787,
                98,
                527,
                172,
                488,
                785,
                147,
                273,
                658,
                263,
                566,
                225,
                140,
                629,
                376,
                409,
                312,
                67,
                750,
                571,
                699,
                278,
                671,
                623,
                779,
                706,
                581,
                431,
                284,
                8,
                704,
                371,
                471,
                267,
                351,
                458,
                727,
                348,
                173,
                87,
                709,
                42,
                680,
                405,
                784,
                655
            ],
            "train_size": 133,
            "val_size": 133
        },
        "wikitext": {
            "train_indices": [
                3084,
                14364,
                23683,
                5243,
                26207,
                29654,
                22522,
                23985,
                21064,
                7921,
                30620,
                34328,
                16535,
                20101,
                16240,
                8324,
                34955,
                3653,
                21886,
                9438,
                4393,
                13663,
                32377,
                971,
                16446,
                20860,
                4523,
                35403,
                16474,
                2236,
                10544,
                14695,
                28429,
                35167,
                29265,
                35271,
                33938,
                34845,
                26515,
                28456,
                3626,
                27979,
                22598,
                2777,
                34981,
                22197,
                25949,
                415,
                5196,
                25752,
                19013,
                10833,
                36463,
                8396,
                32496,
                6442,
                31945,
                7999,
                20654,
                28981,
                27856,
                18878,
                7607,
                16655,
                28138,
                13576
            ],
            "val_indices": [
                315,
                1470,
                2425,
                536,
                2683,
                3036,
                2306,
                2456,
                2157,
                811,
                3135,
                3515,
                1693,
                2058,
                1663,
                852,
                3579,
                374,
                2241,
                966,
                449,
                1399,
                3315,
                99,
                1684,
                2136,
                463,
                3625,
                1687,
                228,
                1079,
                1504,
                2911,
                3601,
                2996,
                3611,
                3475,
                3568,
                2715,
                2913,
                371,
                2865,
                2314,
                284,
                3582,
                2273,
                2657,
                42,
                532,
                2637,
                1947,
                1109,
                3733,
                859,
                3327,
                659,
                3271,
                819,
                2115,
                2967,
                2852,
                1933,
                779,
                1705,
                2881,
                1390
            ],
            "train_size": 66,
            "val_size": 66
        },
        "mmlu": {
            "train_indices": [
                1179,
                5493,
                9057,
                2005,
                10022,
                11340,
                8613,
                9172,
                8055,
                3029,
                11710,
                13128,
                6323,
                7687,
                6210,
                3183,
                13368,
                1397,
                8370,
                3609,
                1680,
                5225,
                12382,
                371,
                6289,
                7977,
                1730,
                13539,
                6300,
                855,
                4032,
                5620,
                10872,
                13449,
                11191,
                13488,
                12979,
                13325,
                10140,
                10882,
                1386,
                10699,
                8642,
                1062,
                13377,
                8489,
                9923,
                159,
                1987,
                9848,
                7271,
                4143,
                13944,
                3211,
                12427,
                2463,
                12216,
                3059,
                7898,
                11083,
                10653,
                7219,
                2909,
                6369,
                10760,
                5192,
                11459,
                8009,
                11138,
                13287,
                3126,
                11755,
                11304,
                12404,
                11785,
                6451,
                2242,
                13522,
                13067,
                3958,
                12576,
                3836,
                8270,
                9549,
                1210,
                13870,
                4264,
                13534,
                1687,
                9068,
                2965,
                8395,
                13500,
                2533,
                4699,
                11322,
                4523,
                9730,
                3871,
                2419,
                10819,
                6470,
                7040,
                5371,
                1158,
                12891,
                9827,
                12024,
                4784,
                11535,
                10713,
                13390,
                12137,
                9989,
                7411,
                4891,
                148,
                12112,
                6378,
                8109,
                4606,
                6037,
                7882,
                12497,
                5993,
                2975,
                1497,
                12186,
                731,
                11688,
                6976,
                13488
            ],
            "val_indices": [
                128,
                598,
                987,
                218,
                1092,
                1236,
                939,
                1000,
                878,
                330,
                1276,
                1431,
                689,
                838,
                677,
                347,
                1457,
                152,
                912,
                393,
                183,
                569,
                1350,
                40,
                685,
                869,
                188,
                1476,
                686,
                93,
                439,
                612,
                1185,
                1466,
                1220,
                1470,
                1415,
                1452,
                1105,
                1186,
                151,
                1166,
                942,
                115,
                1458,
                925,
                1082,
                17,
                216,
                1073,
                792,
                451,
                1520,
                350,
                1354,
                268,
                1332,
                333,
                861,
                1208,
                1161,
                787,
                317,
                694,
                1173,
                566,
                1249,
                873,
                1214,
                1448,
                340,
                1281,
                1232,
                1352,
                1284,
                703,
                244,
                1474,
                1424,
                431,
                1371,
                418,
                901,
                1041,
                132,
                1512,
                464,
                1475,
                183,
                988,
                323,
                915,
                1471,
                276,
                512,
                1234,
                493,
                1060,
                422,
                263,
                1179,
                705,
                767,
                585,
                126,
                1405,
                1071,
                1310,
                521,
                1257,
                1168,
                1459,
                1323,
                1089,
                808,
                533,
                16,
                1320,
                695,
                884,
                502,
                658,
                859,
                1362,
                653,
                324,
                163,
                1328,
                79,
                1274,
                760,
                1470
            ],
            "train_size": 132,
            "val_size": 132
        },
        "ai2_arc": {
            "train_indices": [
                94,
                437,
                721,
                159,
                798,
                903,
                686,
                730,
                641,
                241,
                933,
                1046,
                503,
                612,
                494,
                253,
                1065,
                111,
                667,
                287,
                133,
                416,
                986,
                29,
                501,
                635,
                137,
                1078,
                502,
                68,
                321,
                447,
                866,
                1071,
                891,
                1074,
                1034,
                1061,
                808,
                867,
                110,
                852,
                688,
                84,
                1066,
                676,
                790,
                12,
                158,
                784,
                579,
                330,
                1111
            ],
            "val_indices": [
                25,
                116,
                192,
                42,
                213,
                241,
                183,
                195,
                171,
                64,
                249,
                279,
                134,
                163,
                132,
                67,
                284,
                29,
                178,
                76,
                35,
                111,
                263,
                7,
                133,
                169,
                36,
                288,
                134,
                18,
                85,
                119,
                231,
                286,
                238,
                287,
                276,
                283,
                215,
                231,
                29,
                227,
                184,
                22,
                284,
                180,
                211,
                3,
                42,
                209,
                154,
                88,
                296
            ],
            "train_size": 53,
            "val_size": 53
        }
    }
}